app/__init__.py
app/app.py
motionsenseapp-0.0.2.dist-info/METADATA
motionsenseapp-0.0.2.dist-info/WHEEL
motionsenseapp-0.0.2.dist-info/top_level.txt
motionsenseapp-0.0.2.dist-info/RECORD
