Metadata-Version: 2.1
Name: motionsenseapp
Version: 0.0.2
Summary: Motion Sense
Author: Cole Hagen
Author-email: hagencolej@gmail.com
Classifier: Programming Language :: Python :: 3
Classifier: License :: OSI Approved :: MIT License
Classifier: Operating System :: OS Independent
Requires-Python: >=3.7
Requires-Dist: mediapipe
Requires-Dist: opencv-python-headless
Requires-Dist: plotly
Requires-Dist: pandas
Requires-Dist: numpy
